<?xml version="1.0"?>
<!DOCTYPE package-info SYSTEM "http://www.simplemachines.org/xml/package-info">
<!-- - - - - - - - - - - - - - - - - - - - - - - - - - - - - - - - - - - - - - -
	Package manifest file for Rounded Corners for Quote and Code Blocks
 - - - - - - - - - - - - - - - - - - - - - - - - - - - - - - - - - - - - - - -->
<package-info xmlns="http://www.simplemachines.org/xml/package-info" xmlns:smf="http://www.simplemachines.org/">
	<name>Rounded Corners for Quote and Code Blocks</name>
	<id>BurkeKnight:RCfQCB</id>
	<type>modification</type>
	<version>1.0</version>

	<install for="2.0 - 2.0.99">
		<readme type="file" parsebbc="true">readme.txt</readme>
		<modification>modification.xml</modification>
	</install>
	
	<uninstall for="2.0 - 2.0.99">
		<modification reverse="true">modification.xml</modification>
	</uninstall>
</package-info>